aioplus/__init__.py
aioplus/internal/__init__.py
aioplus/internal/aall.py
aioplus/internal/aany.py
aioplus/internal/abatched.py
aioplus/internal/achain.py
aioplus/internal/acount.py
aioplus/internal/acycle.py
aioplus/internal/aempty.py
aioplus/internal/aenumerate.py
aioplus/internal/afirst.py
aioplus/internal/ahead.py
aioplus/internal/aislice.py
aioplus/internal/alast.py
aioplus/internal/alen.py
aioplus/internal/amax.py
aioplus/internal/amin.py
aioplus/internal/aminmax.py
aioplus/internal/anextify.py
aioplus/internal/anth.py
aioplus/internal/apairwise.py
aioplus/internal/apostpend.py
aioplus/internal/aprepend.py
aioplus/internal/arange.py
aioplus/internal/arepeat.py
aioplus/internal/areversed.py
aioplus/internal/asum.py
aioplus/internal/atabulate.py
aioplus/internal/atail.py
aioplus/internal/atriplewise.py
aioplus/internal/awaitify.py
aioplus/internal/awindowed.py
aioplus/internal/azip.py
aioplus/internal/caller_thread_executor.py
aioplus/internal/utils/__init__.py
aioplus/internal/utils/abc.py
aioplus/internal/utils/typing.py
aioplus/py.typed
aioplus-0.7.0.dist-info/licenses/AUTHORS
aioplus-0.7.0.dist-info/licenses/LICENSE
aioplus-0.7.0.dist-info/METADATA
aioplus-0.7.0.dist-info/WHEEL
aioplus-0.7.0.dist-info/RECORD
