Metadata-Version: 2.4
Name: aioplus
Version: 0.7.0
Summary: Because asyncio.gather() is not enough!
License: MIT
License-File: AUTHORS
License-File: LICENSE
Keywords: async,asyncio,builtins,concurrency,concurrent,executor,futures,iteration,iterator,itertools,more-itertools,python,python3,stdlib
Author: Sergei Y. Bogdanov
Author-email: syubogdanov@outlook.com
Maintainer: Sergei Y. Bogdanov
Maintainer-email: syubogdanov@outlook.com
Requires-Python: >=3.11
Classifier: Development Status :: 4 - Beta
Classifier: Framework :: AsyncIO
Classifier: Intended Audience :: Developers
Classifier: License :: OSI Approved :: MIT License
Classifier: Operating System :: OS Independent
Classifier: Programming Language :: Python
Classifier: Programming Language :: Python :: 3
Classifier: Programming Language :: Python :: 3.11
Classifier: Programming Language :: Python :: 3.12
Classifier: Programming Language :: Python :: 3.13
Classifier: Programming Language :: Python :: 3.14
Classifier: Topic :: Software Development :: Libraries
Classifier: Topic :: Utilities
Classifier: Typing :: Typed
Project-URL: Documentation, https://aioplus.readthedocs.io
Project-URL: Homepage, https://github.com/syubogdanov/aioplus
Project-URL: Repository, https://github.com/syubogdanov/aioplus
